grey_model/__init__.py
grey_model/hello.py
grey_model/win.py
grey_model/need/1.png
grey_model/need/2.png
grey_model-0.0.3.9.dist-info/METADATA
grey_model-0.0.3.9.dist-info/WHEEL
grey_model-0.0.3.9.dist-info/top_level.txt
grey_model-0.0.3.9.dist-info/RECORD
