Metadata-Version: 2.1
Name: grey-model
Version: 0.0.3.9
Summary: 灰色系统包，目前只有一个功能，未来会有很多！
Home-page: http://math.halashuo.cn/
Author: Yiming Zeng
Author-email: romtance@163.com
License: UNKNOWN
Keywords: python,grey model,prediction
Platform: UNKNOWN
Classifier: Development Status :: 1 - Planning
Classifier: Intended Audience :: Developers
Classifier: Programming Language :: Python :: 3
Classifier: Operating System :: Unix
Classifier: Operating System :: MacOS :: MacOS X
Classifier: Operating System :: Microsoft :: Windows
Requires-Dist: statsmodels
Requires-Dist: matplotlib
Requires-Dist: pandas
Requires-Dist: numpy
Requires-Dist: pmdarima
